odoo/addons/base_m2m_custom_field/README.rst
odoo/addons/base_m2m_custom_field/__init__.py
odoo/addons/base_m2m_custom_field/__manifest__.py
odoo/addons/base_m2m_custom_field/fields.py
odoo/addons/base_m2m_custom_field/i18n/base_m2m_custom_field.pot
odoo/addons/base_m2m_custom_field/readme/CONTRIBUTORS.rst
odoo/addons/base_m2m_custom_field/readme/DESCRIPTION.rst
odoo/addons/base_m2m_custom_field/readme/USAGE.rst
odoo/addons/base_m2m_custom_field/static/description/icon.png
odoo/addons/base_m2m_custom_field/static/description/index.html
odoo14_addon_base_m2m_custom_field-14.0.1.1.0.dist-info/METADATA
odoo14_addon_base_m2m_custom_field-14.0.1.1.0.dist-info/WHEEL
odoo14_addon_base_m2m_custom_field-14.0.1.1.0.dist-info/top_level.txt
odoo14_addon_base_m2m_custom_field-14.0.1.1.0.dist-info/RECORD
